[
  {
    "id": "stockpile_all",
    "name": "All Goods",
    "desc": "Accepts any item",
    "mode": "pull_only",
    "target_fill": 0.9,
    "filters": { "allow_tags": ["*"], "deny_tags": [] }
  },
  {
    "id": "stockpile_wood",
    "name": "Wood",
    "desc": "Accepts logs, planks",
    "mode": "pull_only",
    "target_fill": 0.8,
    "filters": { "allow_tags": ["wood"], "deny_tags": [] }
  },
  {
    "id": "stockpile_ore",
    "name": "Ore",
    "desc": "Accepts metal ores and ingots",
    "mode": "pull_only",
    "target_fill": 0.8,
    "filters": { "allow_tags": ["ore","ingot","metal"], "deny_tags": [] }
  }
]

